{
  "question_filename": "P3_1_06_00042_87677.png",
  "id": "00042_87677",
  "question_info": [
    {
      "question_grade": "P3",
      "question_term": 1,
      "question_unit": "06",
      "question_topic": "3106007",
      "question_topic_name": "분자를 이용하여 분모가 같은 분수의 크기 비교하기",
      "question_type1": "단답형",
      "question_type2": 2,
      "question_condition": 0,
      "question_sector1": "문제해결",
      "question_sector2": "수와 연산",
      "question_step": "실생활응용",
      "question_difficulty": 2,
      "question_contents": 0
    }
  ],
  "OCR_info": [
    {
      "figure_text": null,
      "question_text": "같은 크기의 컵에 우유를 가득 따라 준호는 $ \\frac{6}{7} $만큼 마셨고, 승연이는 $ \\frac{4}{7} $만큼 마셨습니다. 누가 우유를 더 많이 마셨습니까?",
      "question_bbox": [
        {
          "type": "line",
          "bbox": [
            18,
            1,
            721,
            36
          ],
          "text": null
        },
        {
          "type": "paragraph",
          "bbox": [
            16,
            1,
            723,
            38
          ],
          "text": "같은 크기의 컵에 우유를 가득 따라 준호는 $ \\frac{6}{7} $만큼 마셨고, 승연이는 $ \\frac{4}{7} $만큼 마셨습니다. 누가 우유를 더 많이 마셨습니까?"
        }
      ]
    }
  ]
}