{
  "question_filename": "P3_1_01_00040_17864.png",
  "id": "00040_17864",
  "question_info": [
    {
      "question_grade": "P3",
      "question_term": 1,
      "question_unit": "01",
      "question_topic": "3101015",
      "question_topic_name": "십의 자리에서 받아내림이 있는 뺄셈 알아보기",
      "question_type1": "선택형",
      "question_type2": 2,
      "question_condition": 0,
      "question_sector1": "이해",
      "question_sector2": "수와 연산",
      "question_step": "기본",
      "question_difficulty": 2,
      "question_contents": 0
    }
  ],
  "OCR_info": [
    {
      "figure_text": null,
      "question_text": "$6\\square7$에 $274$를 더했더니 $881$이 나왔습니다. $\\square$ 안에 들어가야 할 숫자는 얼마입니까?  ①$2$ ②$4$ ③$0$ ④$8$ ⑤$1$",
      "question_bbox": [
        {
          "type": "line",
          "bbox": [
            18,
            1,
            497,
            17
          ],
          "text": null
        },
        {
          "type": "line",
          "bbox": [
            20,
            21,
            53,
            41
          ],
          "text": null
        },
        {
          "type": "line",
          "bbox": [
            20,
            43,
            53,
            63
          ],
          "text": null
        },
        {
          "type": "line",
          "bbox": [
            20,
            65,
            54,
            85
          ],
          "text": null
        },
        {
          "type": "line",
          "bbox": [
            20,
            87,
            53,
            107
          ],
          "text": null
        },
        {
          "type": "line",
          "bbox": [
            20,
            109,
            49,
            129
          ],
          "text": null
        },
        {
          "type": "paragraph",
          "bbox": [
            16,
            1,
            499,
            130
          ],
          "text": "$6\\square7$에 $274$를 더했더니 $881$이 나왔습니다. $\\square$ 안에 들어가야 할 숫자는 얼마입니까?  ①$2$ ②$4$ ③$0$ ④$8$ ⑤$1$"
        }
      ]
    }
  ]
}