{
  "question_filename": "P3_2_01_00043_49429.png",
  "id": "00043_49429",
  "question_info": [
    {
      "question_grade": "P3",
      "question_term": 2,
      "question_unit": "01",
      "question_topic": "3201008",
      "question_topic_name": "(몇십몇)x(몇십) 알아보기",
      "question_type1": "단답형",
      "question_type2": 2,
      "question_condition": 0,
      "question_sector1": "문제해결",
      "question_sector2": "수와 연산",
      "question_step": "실생활응용",
      "question_difficulty": 2,
      "question_contents": 0
    }
  ],
  "OCR_info": [
    {
      "figure_text": null,
      "question_text": "강당에 의자가 한 줄에 $37$개씩 $50$줄로 놓여 있습니다. 강당에 놓인 의자는 모두 몇 개입니까?",
      "question_bbox": [
        {
          "type": "line",
          "bbox": [
            18,
            1,
            543,
            17
          ],
          "text": null
        },
        {
          "type": "paragraph",
          "bbox": [
            16,
            1,
            545,
            19
          ],
          "text": "강당에 의자가 한 줄에 $37$개씩 $50$줄로 놓여 있습니다. 강당에 놓인 의자는 모두 몇 개입니까?"
        }
      ]
    }
  ]
}