{
  "question_filename": "P3_2_03_00043_53701.png",
  "id": "00043_53701",
  "question_info": [
    {
      "question_grade": "P3",
      "question_term": 2,
      "question_unit": "03",
      "question_topic": "3203004",
      "question_topic_name": "지름의 성질 알아보기",
      "question_type1": "단답형",
      "question_type2": 1,
      "question_condition": 0,
      "question_sector1": "이해",
      "question_sector2": "도형과 측정",
      "question_step": "기본",
      "question_difficulty": 2,
      "question_contents": 0
    }
  ],
  "OCR_info": [
    {
      "figure_text": null,
      "question_text": "다음 중 바르게 설명한 것을 찾아 기호를 쓰시오. ㉠ 반지름이$ 1 \\mathrm{~cm} $인 원의 지름은 $ 3 \\mathrm{~cm} $입니다. ㉡ 지름이 $ 8 \\mathrm{~cm} $인 원의 반지름은 $ 4 \\mathrm{~cm} $입니다. ㉢ 지름이 반지름의 $2$배가 아닌 원도 있습니다. ㉣ 한 원에서 반지름은 모두 다릅니다.",
      "question_bbox": [
        {
          "type": "line",
          "bbox": [
            18,
            1,
            291,
            16
          ],
          "text": null
        },
        {
          "type": "line",
          "bbox": [
            23,
            21,
            285,
            54
          ],
          "text": null
        },
        {
          "type": "line",
          "bbox": [
            25,
            54,
            288,
            73
          ],
          "text": null
        },
        {
          "type": "line",
          "bbox": [
            25,
            73,
            290,
            95
          ],
          "text": null
        },
        {
          "type": "line",
          "bbox": [
            19,
            95,
            245,
            123
          ],
          "text": null
        },
        {
          "type": "paragraph",
          "bbox": [
            16,
            1,
            292,
            123
          ],
          "text": "다음 중 바르게 설명한 것을 찾아 기호를 쓰시오. ㉠ 반지름이$ 1 \\mathrm{~cm} $인 원의 지름은 $ 3 \\mathrm{~cm} $입니다. ㉡ 지름이 $ 8 \\mathrm{~cm} $인 원의 반지름은 $ 4 \\mathrm{~cm} $입니다. ㉢ 지름이 반지름의 $2$배가 아닌 원도 있습니다. ㉣ 한 원에서 반지름은 모두 다릅니다."
        }
      ]
    }
  ]
}