{
  "question_filename": "P3_2_05_00042_54571.png",
  "id": "00042_54571",
  "question_info": [
    {
      "question_grade": "P3",
      "question_term": 2,
      "question_unit": "05",
      "question_topic": "3205011",
      "question_topic_name": "들이의 덧셈 알아보기",
      "question_type1": "단답형",
      "question_type2": 2,
      "question_condition": 0,
      "question_sector1": "문제해결",
      "question_sector2": "도형과 측정",
      "question_step": "실생활응용",
      "question_difficulty": 2,
      "question_contents": 0
    }
  ],
  "OCR_info": [
    {
      "figure_text": null,
      "question_text": "물 $ 2 \\mathrm{~L} 500 \\mathrm{~mL} $가 들어 있는 물통에 $ 1 \\mathrm{~L} 100 \\mathrm{~mL} $의 물을 더 부었습니다. 물통에 들어 있는 물의 양은 모두 몇 $ L $ 몇 $ \\mathrm{mL} $입니까?",
      "question_bbox": [
        {
          "type": "line",
          "bbox": [
            18,
            1,
            707,
            17
          ],
          "text": null
        },
        {
          "type": "paragraph",
          "bbox": [
            16,
            1,
            709,
            21
          ],
          "text": "물 $ 2 \\mathrm{~L} 500 \\mathrm{~mL} $가 들어 있는 물통에 $ 1 \\mathrm{~L} 100 \\mathrm{~mL} $의 물을 더 부었습니다. 물통에 들어 있는 물의 양은 모두 몇 $ L $ 몇 $ \\mathrm{mL} $입니까?"
        }
      ]
    }
  ]
}