{
  "question_filename": "P3_2_05_00050_20311.png",
  "id": "00050_20311",
  "question_info": [
    {
      "question_grade": "P3",
      "question_term": 2,
      "question_unit": "05",
      "question_topic": "3205020",
      "question_topic_name": "kg보다 더 큰 무게의 단위 알아보기",
      "question_type1": "단답형",
      "question_type2": 2,
      "question_condition": 0,
      "question_sector1": "문제해결",
      "question_sector2": "도형과 측정",
      "question_step": "실생활응용",
      "question_difficulty": 2,
      "question_contents": 0
    }
  ],
  "OCR_info": [
    {
      "figure_text": null,
      "question_text": "네 농장에서 수확한 인삼을 $ 2 t $까지 실을 수 있는 트럭 여러 대로 한 번에 옮기려고 합니다. 트럭은 적어도 몇 대 필요합니까?",
      "question_bbox": [
        {
          "type": "line",
          "bbox": [
            19,
            1,
            713,
            18
          ],
          "text": null
        },
        {
          "type": "paragraph",
          "bbox": [
            17,
            1,
            715,
            21
          ],
          "text": "네 농장에서 수확한 인삼을 $ 2 t $까지 실을 수 있는 트럭 여러 대로 한 번에 옮기려고 합니다. 트럭은 적어도 몇 대 필요합니까?"
        }
      ]
    }
  ]
}