{
  "question_filename": "P4_1_04_00042_26977.png",
  "id": "00042_26977",
  "question_info": [
    {
      "question_grade": "P4",
      "question_term": 1,
      "question_unit": "04",
      "question_topic": "4104001",
      "question_topic_name": "평면도형을 위쪽, 아래쪽으로 밀기",
      "question_type1": "단답형",
      "question_type2": 1,
      "question_condition": 0,
      "question_sector1": "이해",
      "question_sector2": "도형과 측정",
      "question_step": "기본",
      "question_difficulty": 3,
      "question_contents": 0
    }
  ],
  "OCR_info": [
    {
      "figure_text": null,
      "question_text": "왼쪽 도형을 오른쪽으로 밀었을 때 생기는 모양을 그린 것입니다. 물음에 답하시오. (1) 왼쪽 도형 위에 투명 종이를 대고 본을 떠 오른쪽 도형 위에 놓으면 꼭 맞게 (겹쳐집니다, 겹쳐지지 않습니다). (2) 왼쪽 도형을 오른쪽으로 밀면 모양과 크기가 (변합니다, 변하지 않습니다).",
      "question_bbox": [
        {
          "type": "line",
          "bbox": [
            20,
            1,
            483,
            17
          ],
          "text": null
        },
        {
          "type": "line",
          "bbox": [
            18,
            107,
            648,
            127
          ],
          "text": null
        },
        {
          "type": "line",
          "bbox": [
            18,
            132,
            456,
            149
          ],
          "text": null
        },
        {
          "type": "image",
          "bbox": [
            18,
            20,
            241,
            107
          ],
          "text": null
        },
        {
          "type": "paragraph",
          "bbox": [
            18.23,
            0,
            485.23,
            17.65
          ],
          "text": "왼쪽 도형을 오른쪽으로 밀었을 때 생기는 모양을 그린 것입니다. 물음에 답하시오."
        },
        {
          "type": "paragraph",
          "bbox": [
            15.23,
            107.65,
            651.23,
            152.65
          ],
          "text": "(1) 왼쪽 도형 위에 투명 종이를 대고 본을 떠 오른쪽 도형 위에 놓으면 꼭 맞게 (겹쳐집니다, 겹쳐지지 않습니다). (2) 왼쪽 도형을 오른쪽으로 밀면 모양과 크기가 (변합니다, 변하지 않습니다)."
        }
      ]
    }
  ]
}