{
  "question_filename": "P3_2_02_23805_69379.png",
  "id": "23805_69379",
  "question_info": [
    {
      "question_grade": "P3",
      "question_term": 2,
      "question_unit": "02",
      "question_topic": "3202005",
      "question_topic_name": "나머지가 있는 (몇십몇)÷(몇) 알아보기",
      "question_type1": "서술",
      "question_type2": 2,
      "question_condition": 0,
      "question_sector1": "이해",
      "question_sector2": "수와 연산",
      "question_step": "실생활응용",
      "question_difficulty": 2,
      "question_contents": 0,
      "question_rtime": 101,
      "question_success_rate": 91.06
    }
  ],
  "OCR_info": [
    {
      "figure_text": null,
      "question_text": "사탕이 $5$ 개씩 $7$ 봉지에 담겨 있습니다. 한 명이 $6$ 개씩 먹는다면 몇 명이 먹을 수 있고 몇 개가 남는지 구해 보세요.",
      "question_bbox": [
        {
          "type": "line",
          "bbox": [
            1,
            3,
            586,
            28
          ],
          "text": null
        },
        {
          "type": "line",
          "bbox": [
            2,
            33,
            502,
            58
          ],
          "text": null
        },
        {
          "type": "paragraph",
          "bbox": [
            1,
            2,
            588,
            59
          ],
          "text": "사탕이 $5$ 개씩 $7$ 봉지에 담겨 있습니다. 한 명이 $6$ 개씩 먹는다면 몇 명이 먹을 수 있고 몇 개가 남는지 구해 보세요. "
        }
      ]
    }
  ]
}