{
  "question_filename": "P3_2_04_32812_126470.png",
  "id": "32812_126470",
  "question_info": [
    {
      "question_grade": "P3",
      "question_term": 2,
      "question_unit": "04",
      "question_topic": "3204005",
      "question_topic_name": "분수로 나타내기",
      "question_type1": "서술",
      "question_type2": 1,
      "question_condition": 0,
      "question_sector1": "이해",
      "question_sector2": "수와 연산",
      "question_step": "기본",
      "question_difficulty": 2,
      "question_contents": 0,
      "question_rtime": 85,
      "question_success_rate": 79.14
    }
  ],
  "OCR_info": [
    {
      "figure_text": null,
      "question_text": "㉠과 ㉡의 합을 구해 보세요. $\\bullet$ $42$를 $6$씩 묶으면 ㉠ 묶음이 됩니다. $\\bullet$ $30$은 $42$의 $\\frac{㉡}{㉠}$입니다.",
      "question_bbox": [
        {
          "type": "line",
          "bbox": [
            3,
            3,
            271,
            28
          ],
          "text": null
        },
        {
          "type": "line",
          "bbox": [
            138,
            68,
            471,
            93
          ],
          "text": null
        },
        {
          "type": "line",
          "bbox": [
            138,
            102,
            343,
            147
          ],
          "text": null
        },
        {
          "type": "paragraph",
          "bbox": [
            1,
            2,
            494,
            163
          ],
          "text": "㉠과 ㉡의 합을 구해 보세요. $\\bullet$ $42$를 $6$씩 묶으면 ㉠ 묶음이 됩니다. $\\bullet$ $30$은 $42$의 $\\frac{㉡}{㉠}$입니다."
        }
      ]
    }
  ]
}