{
  "question_filename": "P3_1_01_00043_33238.png",
  "id": "00043_33238",
  "question_info": [
    {
      "question_grade": "P3",
      "question_term": 1,
      "question_unit": "01",
      "question_topic": "3101015",
      "question_topic_name": "십의 자리에서 받아내림이 있는 뺄셈 알아보기",
      "question_type1": "단답형",
      "question_type2": 1,
      "question_condition": 0,
      "question_sector1": "계산",
      "question_sector2": "수와 연산",
      "question_step": "기본",
      "question_difficulty": 3,
      "question_contents": 0
    }
  ],
  "OCR_info": [
    {
      "figure_text": null,
      "question_text": "뺄셈을 하시오.",
      "question_bbox": [
        {
          "type": "line",
          "bbox": [
            18,
            1,
            103,
            16
          ],
          "text": null
        },
        {
          "type": "line",
          "bbox": [
            18,
            24,
            91,
            67
          ],
          "text": null
        },
        {
          "type": "line",
          "bbox": [
            110,
            24,
            187,
            67
          ],
          "text": null
        },
        {
          "type": "image",
          "bbox": [
            19.01,
            23.39,
            187.33,
            70.11
          ],
          "text": null
        },
        {
          "type": "paragraph",
          "bbox": [
            17.73,
            0,
            104.13,
            14.43
          ],
          "text": "뺄셈을 하시오."
        }
      ]
    }
  ]
}