{
  "question_filename": "P3_1_05_00042_26565.png",
  "id": "00042_26565",
  "question_info": [
    {
      "question_grade": "P3",
      "question_term": 1,
      "question_unit": "05",
      "question_topic": "3105022",
      "question_topic_name": "시, 분, 초 단위의 시간의 덧셈과 뺄셈의 활용",
      "question_type1": "단답형",
      "question_type2": 2,
      "question_condition": 0,
      "question_sector1": "문제해결",
      "question_sector2": "수와 연산",
      "question_step": "실생활응용",
      "question_difficulty": 1,
      "question_contents": 0
    }
  ],
  "OCR_info": [
    {
      "figure_text": null,
      "question_text": "통나무를 $4$도막으로 자르려고 합니다. 한 번 자르는 데 $5$분 $30$초가 걸리고, 한 번 자른 후 $2$분씩 쉰다고 할 때, 통나무를 $4$도막으로 자르는 데 걸리는 시간은 모두 몇 분 몇 초입니까?",
      "question_bbox": [
        {
          "type": "line",
          "bbox": [
            18,
            1,
            794,
            17
          ],
          "text": null
        },
        {
          "type": "line",
          "bbox": [
            18,
            22,
            257,
            39
          ],
          "text": null
        },
        {
          "type": "paragraph",
          "bbox": [
            16,
            1,
            797,
            41
          ],
          "text": "통나무를 $4$도막으로 자르려고 합니다. 한 번 자르는 데 $5$분 $30$초가 걸리고, 한 번 자른 후 $2$분씩 쉰다고 할 때, 통나무를 $4$도막으로 자르는 데 걸리는 시간은 모두 몇 분 몇 초입니까?"
        }
      ]
    }
  ]
}