{
  "question_filename": "P3_2_05_00050_20462.png",
  "id": "00050_20462",
  "question_info": [
    {
      "question_grade": "P3",
      "question_term": 2,
      "question_unit": "05",
      "question_topic": "3205020",
      "question_topic_name": "kg보다 더 큰 무게의 단위 알아보기",
      "question_type1": "단답형",
      "question_type2": 2,
      "question_condition": 0,
      "question_sector1": "문제해결",
      "question_sector2": "도형과 측정",
      "question_step": "실생활응용",
      "question_difficulty": 1,
      "question_contents": 0
    }
  ],
  "OCR_info": [
    {
      "figure_text": null,
      "question_text": "어느 건물의 화물 승강기에는 최대 $3t$까지 실을 수 있습니다. 이 화물 승강기에 몸무게가 $70kg$인 어른 $5$명이 타고 있습니다. 여기에 한 상자의 무게가 $45kg$인 이삿짐 상자는 몇 개까지 더 실을 수 있습니까?",
      "question_bbox": [
        {
          "type": "line",
          "bbox": [
            18,
            1,
            803,
            17
          ],
          "text": null
        },
        {
          "type": "line",
          "bbox": [
            18,
            22,
            387,
            39
          ],
          "text": null
        },
        {
          "type": "paragraph",
          "bbox": [
            16,
            1,
            804,
            41
          ],
          "text": "어느 건물의 화물 승강기에는 최대 $3t$까지 실을 수 있습니다. 이 화물 승강기에 몸무게가 $70kg$인 어른 $5$명이 타고 있습니다. 여기에 한 상자의 무게가 $45kg$인 이삿짐 상자는 몇 개까지 더 실을 수 있습니까?"
        }
      ]
    }
  ]
}