{
  "question_filename": "P3_2_05_00043_57383.png",
  "id": "00043_57383",
  "question_info": [
    {
      "question_grade": "P3",
      "question_term": 2,
      "question_unit": "05",
      "question_topic": "3205003",
      "question_topic_name": "컵의 수를 비교하여 들이 비교하기",
      "question_type1": "단답형",
      "question_type2": 2,
      "question_condition": 0,
      "question_sector1": "문제해결",
      "question_sector2": "도형과 측정",
      "question_step": "실생활응용",
      "question_difficulty": 2,
      "question_contents": 0
    }
  ],
  "OCR_info": [
    {
      "figure_text": null,
      "question_text": "그릇 ㉮, ㉯, ㉰에 물을 가득 담아 크기가 같은 어항 $3$개를 채우려고 합니다. 각각 다음 횟수만큼 어항에 물을 부으면 물이 가득 찬다고 할 때 들이가 많은 그릇의 순서대로 기호를 쓰시오.  ㉮ : $17$회 ㉯ : $15$회 ㉰ : $20$회",
      "question_bbox": [
        {
          "type": "line",
          "bbox": [
            18,
            1,
            799,
            17
          ],
          "text": null
        },
        {
          "type": "line",
          "bbox": [
            18,
            22,
            271,
            38
          ],
          "text": null
        },
        {
          "type": "line",
          "bbox": [
            27,
            43,
            218,
            79
          ],
          "text": null
        },
        {
          "type": "paragraph",
          "bbox": [
            16,
            1,
            804,
            74
          ],
          "text": "그릇 ㉮, ㉯, ㉰에 물을 가득 담아 크기가 같은 어항 $3$개를 채우려고 합니다. 각각 다음 횟수만큼 어항에 물을 부으면 물이 가득 찬다고 할 때 들이가 많은 그릇의 순서대로 기호를 쓰시오.  ㉮ : $17$회 ㉯ : $15$회 ㉰ : $20$회"
        }
      ]
    }
  ]
}