{
  "question_filename": "P4_1_02_00042_28197.png",
  "id": "00042_28197",
  "question_info": [
    {
      "question_grade": "P4",
      "question_term": 1,
      "question_unit": "02",
      "question_topic": "4102004",
      "question_topic_name": "각도기와 자를 이용하여 각 그리기",
      "question_type1": "단답형",
      "question_type2": 1,
      "question_condition": 0,
      "question_sector1": "문제해결",
      "question_sector2": "도형과 측정",
      "question_step": "기본",
      "question_difficulty": 3,
      "question_contents": 0
    }
  ],
  "OCR_info": [
    {
      "figure_text": null,
      "question_text": "다음과 같은 순서에 따라 삼각형 ㄱㄴㄷ을 그려 보시오. ① 점 ㄴ을 각의 꼭짓점으로 하여 각도가 $45^{\\circ}$인 각을 그립니다. ② 점 ㄷ을 각의 꼭짓점으로 하여 각도가 $45^{\\circ}$인 각을 그립니다. ③ 점 ㄴ과 점 ㄷ에서 그은 각의 변이 만나는 점 ㄱ을 찾아 삼각형 ㄱㄴㄷ을 완성합니다.",
      "question_bbox": [
        {
          "type": "line",
          "bbox": [
            18,
            1,
            329,
            17
          ],
          "text": null
        },
        {
          "type": "line",
          "bbox": [
            22,
            21,
            379,
            55
          ],
          "text": null
        },
        {
          "type": "line",
          "bbox": [
            21,
            55,
            385,
            73
          ],
          "text": null
        },
        {
          "type": "line",
          "bbox": [
            19,
            73,
            520,
            102
          ],
          "text": null
        },
        {
          "type": "image",
          "bbox": [
            18,
            124,
            194,
            240
          ],
          "text": null
        },
        {
          "type": "paragraph",
          "bbox": [
            16,
            1,
            804,
            103
          ],
          "text": "다음과 같은 순서에 따라 삼각형 ㄱㄴㄷ을 그려 보시오. ① 점 ㄴ을 각의 꼭짓점으로 하여 각도가 $45^{\\circ}$인 각을 그립니다. ② 점 ㄷ을 각의 꼭짓점으로 하여 각도가 $45^{\\circ}$인 각을 그립니다. ③ 점 ㄴ과 점 ㄷ에서 그은 각의 변이 만나는 점 ㄱ을 찾아 삼각형 ㄱㄴㄷ을 완성합니다."
        }
      ]
    }
  ]
}